mcp_document_processor/__init__.py
mcp_document_processor/__main__.py
mcp_document_processor/server.py
mcp_document_processor-0.1.4.dist-info/METADATA
mcp_document_processor-0.1.4.dist-info/WHEEL
mcp_document_processor-0.1.4.dist-info/entry_points.txt
mcp_document_processor-0.1.4.dist-info/top_level.txt
mcp_document_processor-0.1.4.dist-info/RECORD
