Metadata-Version: 2.4
Name: mcp-document-processor
Version: 0.1.4
Summary: A simple document processor MCP server
Author: dever1995
Requires-Python: >=3.10
Requires-Dist: mcp>=1.25.0
